echo_assigner/__init__.py
echo_assigner/config.py
echo_assigner/main.py
echo_assigner/database/__init__.py
echo_assigner/database/pitchClassData.sqlite
echo_assigner/database/pitchclass.py
echo_assigner/database/statistic.py
echo_assigner/database/statisticData.sqlite
echo_assigner/database/sample/1.mid
echo_assigner/database/sample/10.mid
echo_assigner/database/sample/11.mid
echo_assigner/database/sample/12.mid
echo_assigner/database/sample/13.mid
echo_assigner/database/sample/14.mid
echo_assigner/database/sample/15.mid
echo_assigner/database/sample/16.mid
echo_assigner/database/sample/17.mid
echo_assigner/database/sample/18.mid
echo_assigner/database/sample/19.mid
echo_assigner/database/sample/2.mid
echo_assigner/database/sample/20.mid
echo_assigner/database/sample/21.mid
echo_assigner/database/sample/22.mid
echo_assigner/database/sample/23.mid
echo_assigner/database/sample/24.mid
echo_assigner/database/sample/25.mid
echo_assigner/database/sample/26.mid
echo_assigner/database/sample/27.mid
echo_assigner/database/sample/28.mid
echo_assigner/database/sample/29.mid
echo_assigner/database/sample/3.mid
echo_assigner/database/sample/30.mid
echo_assigner/database/sample/4.mid
echo_assigner/database/sample/5.mid
echo_assigner/database/sample/6.mid
echo_assigner/database/sample/7.mid
echo_assigner/database/sample/8.mid
echo_assigner/database/sample/9.mid
echo_assigner/database/sample/__init__.py
echo_assigner/models/__init__.py
echo_assigner/models/baseModel.py
echo_assigner/models/pitchclassModel.py
echo_assigner/models/statisticModel.py
echo_assigner/src/__init__.py
echo_assigner/src/create.py
echo_assigner/src/cui.py
echo_assigner/src/reshape.py
echo_assigner/src/autoharmonizer/__init__.py
echo_assigner/src/autoharmonizer/config.py
echo_assigner/src/autoharmonizer/create_chord.py
echo_assigner/src/autoharmonizer/harmonizer.py
echo_assigner/src/autoharmonizer/loader.py
echo_assigner/src/autoharmonizer/model.py
echo_assigner/utils/__init__.py
echo_assigner-0.1.0.dist-info/LICENSE
echo_assigner-0.1.0.dist-info/METADATA
echo_assigner-0.1.0.dist-info/WHEEL
echo_assigner-0.1.0.dist-info/top_level.txt
echo_assigner-0.1.0.dist-info/RECORD
